{
  "git": {
    "commitMessage": "chore: release v${version}",
    "tagName": "v${version}",
    "requireCleanWorkingDir": true
  },
  "plugins": {
    "@release-it/conventional-changelog": {
      "preset": {
        "name": "conventionalcommits",
        "types": [
          { "type": "feat", "section": "Features" },
          { "type": "fix", "section": "Bug Fixes" },
          { "type": "docs", "section": "Documentation" },
          { "type": "chore", "section": "Chores" },
          { "type": "style", "section": "Styles" },
          { "type": "refactor", "section": "Code Refactoring" },
          { "type": "perf", "section": "Performance Improvements" },
          { "type": "test", "section": "Tests" }
        ]
      },
      "infile": "CHANGELOG.md"
    }
  },
  "github": {
    "release": true
  },
  "npm": {
    "publish": true
  },
  "hooks": {
    "before:init": ["npm run test", "npm run build"]
  }
}
